ols_regressor/__init__.py
ols_regressor/cross_validate.py
ols_regressor/regressor.py
ols_regressor-0.4.4.dist-info/LICENSE
ols_regressor-0.4.4.dist-info/METADATA
ols_regressor-0.4.4.dist-info/WHEEL
ols_regressor-0.4.4.dist-info/RECORD
