Metadata-Version: 2.1
Name: ols_regressor
Version: 0.4.4
Summary: An Ordinary Least Square Regressor
License: MIT
Author: Waleed Mahmood
Requires-Python: >=3.9,<4.0
Classifier: License :: OSI Approved :: MIT License
Classifier: Programming Language :: Python :: 3
Classifier: Programming Language :: Python :: 3.9
Classifier: Programming Language :: Python :: 3.10
Classifier: Programming Language :: Python :: 3.11
Classifier: Programming Language :: Python :: 3.12
Requires-Dist: numpy (>=1.26.3,<2.0.0)
Requires-Dist: pandas (>=2.2.0,<3.0.0)
Requires-Dist: scikit-learn (>=1.4.0,<2.0.0)
